<?xml version="1.0" encoding="utf-8"?>
<!DOCTYPE hibernate-mapping PUBLIC "-//Hibernate/Hibernate Mapping DTD 3.0//EN"
                                   "http://hibernate.sourceforge.net/hibernate-mapping-3.0.dtd">
<!-- 
    Mapping file autogenerated by MyEclipse Persistence Tools
-->
<hibernate-mapping default-lazy="false">
 <class catalog="db_newj2ee" name="org.wingame.dao.TMeeting" table="t_meeting">
  <id name="MId" type="java.lang.Integer">
   <column name="m_id"/>
   <generator class="identity"/>
  </id>
  <property generated="never" lazy="false" name="MTitle" type="java.lang.String">
   <column length="65535" name="m_title" not-null="true"/>
  </property>
  <property generated="never" lazy="false" name="MAddress" type="java.lang.String">
   <column length="65535" name="m_address" not-null="true"/>
  </property>
  <property generated="never" lazy="false" name="MDatetime" type="java.sql.Timestamp">
   <column length="19" name="m_datetime" not-null="true"/>
  </property>
  <property generated="never" lazy="false" name="MFee" type="java.lang.Double">
   <column name="m_fee" not-null="true" precision="22" scale="0"/>
  </property>
  <property generated="never" lazy="false" name="MDeadline" type="java.util.Date">
   <column length="10" name="m_deadline" not-null="true"/>
  </property>
  <set inverse="true" name="TDocuments" sort="unsorted">
   <key>
    <column name="m_id" not-null="true"/>
   </key>
   <one-to-many class="org.wingame.dao.TDocument"/>
  </set>
  <set inverse="true" name="TMeetingStatuses" sort="unsorted">
   <key>
    <column name="m_id" not-null="true"/>
   </key>
   <one-to-many class="org.wingame.dao.TMeetingStatus"/>
  </set>
  <set inverse="true" name="TAnnounces" sort="unsorted">
   <key>
    <column name="m_id" not-null="true"/>
   </key>
   <one-to-many class="org.wingame.dao.TAnnounce"/>
  </set>
 </class>
</hibernate-mapping>
